setup.py
imhotep_pep8/__init__.py
imhotep_pep8/plugin.py
imhotep_pep8.egg-info/PKG-INFO
imhotep_pep8.egg-info/SOURCES.txt
imhotep_pep8.egg-info/dependency_links.txt
imhotep_pep8.egg-info/entry_points.txt
imhotep_pep8.egg-info/top_level.txt