Metadata-Version: 1.1
Name: imhotep-pep8
Version: 0.0.2
Summary: An imhotep plugin for pep8 validation
Home-page: https://github.com/justinabrahms/imhotep_pep8
Author: Justin Abrahms
Author-email: justin@abrah.ms
License: MIT
Platform: UNKNOWN
Requires: pep8
